README.md
setup.py
bsn_sdk/__init__.py
bsn_sdk/operator.py
bsn_sdk.egg-info/PKG-INFO
bsn_sdk.egg-info/SOURCES.txt
bsn_sdk.egg-info/dependency_links.txt
bsn_sdk.egg-info/requires.txt
bsn_sdk.egg-info/top_level.txt
bsn_sdk/common/loggers.py
bsn_sdk/common/myecdsa256.py