Metadata-Version: 2.1
Name: bsn-sdk
Version: 0.1.3
Summary: SDK for BSN(Blockchain Service Network)
Home-page: https://github.com/leeduckgo/bsn_py_sdk
Author: 李大狗Leeduckgo@SUIBE
Author-email: leeduckgo@gmail.com
License: UNKNOWN
Keywords: blockchain bsn
Platform: UNKNOWN
Classifier: Intended Audience :: Developers
Classifier: License :: OSI Approved :: MIT License
